coolapi/__init__.py
coolapi/_core.py
coolapi/Dependent Packages/tornado/LICENSE
coolapi-1.0.3.dist-info/LICENSE
coolapi-1.0.3.dist-info/WHEEL
coolapi-1.0.3.dist-info/METADATA
coolapi-1.0.3.dist-info/RECORD
