Metadata-Version: 2.1
Name: coolapi
Version: 1.0.3
Summary: 简单好用的异步 web 框架
Keywords: coolapi,tornado,flask,fastapi,django,aiohttp,web
Author-email: "lcctoor.com" <lcctoor@outlook.com>
Requires-Python: >=3.7
Classifier: License :: OSI Approved :: Apache Software License
Requires-Dist: tornado
Project-URL: HomePage, https://lcctoor.github.io/lccpy/?package=coolapi
